wm_topic/__init__.py
wm_topic/main.py
wm_topic-0.0.1.dist-info/METADATA
wm_topic-0.0.1.dist-info/WHEEL
wm_topic-0.0.1.dist-info/top_level.txt
wm_topic-0.0.1.dist-info/RECORD
